{
  "content": [
    {
      "content": null,
      "created": "2026-06-28T23:09:01.055727Z",
      "format": null,
      "hash": null,
      "hash_algorithm": null,
      "last_modified": "2026-06-28T23:08:30.423697Z",
      "mimetype": null,
      "name": "session-01-a.ipynb",
      "path": "session-01-a.ipynb",
      "size": 6754,
      "type": "notebook",
      "writable": true
    },
    {
      "content": null,
      "created": "2026-06-28T23:09:01.059727Z",
      "format": null,
      "hash": null,
      "hash_algorithm": null,
      "last_modified": "2026-06-28T23:08:30.427697Z",
      "mimetype": null,
      "name": "session-04-b.ipynb",
      "path": "session-04-b.ipynb",
      "size": 8231,
      "type": "notebook",
      "writable": true
    },
    {
      "content": null,
      "created": "2026-06-28T23:09:01.059727Z",
      "format": null,
      "hash": null,
      "hash_algorithm": null,
      "last_modified": "2026-06-28T23:08:30.431697Z",
      "mimetype": null,
      "name": "session-05-a.ipynb",
      "path": "session-05-a.ipynb",
      "size": 7866,
      "type": "notebook",
      "writable": true
    },
    {
      "content": null,
      "created": "2026-06-28T23:09:01.059727Z",
      "format": null,
      "hash": null,
      "hash_algorithm": null,
      "last_modified": "2026-06-28T23:08:30.431697Z",
      "mimetype": null,
      "name": "session-05-b.ipynb",
      "path": "session-05-b.ipynb",
      "size": 10520,
      "type": "notebook",
      "writable": true
    },
    {
      "content": null,
      "created": "2026-06-28T23:09:01.055727Z",
      "format": null,
      "hash": null,
      "hash_algorithm": null,
      "last_modified": "2026-06-28T23:08:30.423697Z",
      "mimetype": null,
      "name": "session-01-b.ipynb",
      "path": "session-01-b.ipynb",
      "size": 8289,
      "type": "notebook",
      "writable": true
    },
    {
      "content": null,
      "created": "2026-06-28T23:09:01.059727Z",
      "format": null,
      "hash": null,
      "hash_algorithm": null,
      "last_modified": "2026-06-28T23:08:30.431697Z",
      "mimetype": null,
      "name": "session-05.ipynb",
      "path": "session-05.ipynb",
      "size": 18041,
      "type": "notebook",
      "writable": true
    },
    {
      "content": null,
      "created": "2026-06-28T23:09:01.055727Z",
      "format": null,
      "hash": null,
      "hash_algorithm": null,
      "last_modified": "2026-06-28T23:08:30.431697Z",
      "mimetype": null,
      "name": "scratch.ipynb",
      "path": "scratch.ipynb",
      "size": 821,
      "type": "notebook",
      "writable": true
    },
    {
      "content": null,
      "created": "2026-06-28T23:09:01.055727Z",
      "format": null,
      "hash": null,
      "hash_algorithm": null,
      "last_modified": "2026-06-28T23:08:30.423697Z",
      "mimetype": null,
      "name": "session-02-b.ipynb",
      "path": "session-02-b.ipynb",
      "size": 8972,
      "type": "notebook",
      "writable": true
    },
    {
      "content": null,
      "created": "2026-06-28T23:09:01.055727Z",
      "format": null,
      "hash": null,
      "hash_algorithm": null,
      "last_modified": "2026-06-28T23:08:30.423697Z",
      "mimetype": null,
      "name": "session-02-a.ipynb",
      "path": "session-02-a.ipynb",
      "size": 7156,
      "type": "notebook",
      "writable": true
    },
    {
      "content": null,
      "created": "2026-06-28T23:09:01.059727Z",
      "format": null,
      "hash": null,
      "hash_algorithm": null,
      "last_modified": "2026-06-28T23:08:30.427697Z",
      "mimetype": null,
      "name": "session-04.ipynb",
      "path": "session-04.ipynb",
      "size": 15184,
      "type": "notebook",
      "writable": true
    },
    {
      "content": null,
      "created": "2026-06-28T23:09:01.059727Z",
      "format": null,
      "hash": null,
      "hash_algorithm": null,
      "last_modified": "2026-06-28T23:08:30.427697Z",
      "mimetype": null,
      "name": "session-04-a.ipynb",
      "path": "session-04-a.ipynb",
      "size": 7303,
      "type": "notebook",
      "writable": true
    },
    {
      "content": null,
      "created": "2026-06-28T23:09:01.059727Z",
      "format": null,
      "hash": null,
      "hash_algorithm": null,
      "last_modified": "2026-06-28T23:08:30.427697Z",
      "mimetype": null,
      "name": "session-03-b.ipynb",
      "path": "session-03-b.ipynb",
      "size": 8445,
      "type": "notebook",
      "writable": true
    },
    {
      "content": null,
      "created": "2026-06-28T23:09:01.055727Z",
      "format": null,
      "hash": null,
      "hash_algorithm": null,
      "last_modified": "2026-06-28T23:08:30.423697Z",
      "mimetype": null,
      "name": "session-02.ipynb",
      "path": "session-02.ipynb",
      "size": 15791,
      "type": "notebook",
      "writable": true
    },
    {
      "content": null,
      "created": "2026-06-28T23:09:01.059727Z",
      "format": null,
      "hash": null,
      "hash_algorithm": null,
      "last_modified": "2026-06-28T23:08:30.423697Z",
      "mimetype": null,
      "name": "session-03.ipynb",
      "path": "session-03.ipynb",
      "size": 15800,
      "type": "notebook",
      "writable": true
    },
    {
      "content": null,
      "created": "2026-06-28T23:09:01.055727Z",
      "format": null,
      "hash": null,
      "hash_algorithm": null,
      "last_modified": "2026-06-28T23:08:30.419697Z",
      "mimetype": null,
      "name": "session-01.ipynb",
      "path": "session-01.ipynb",
      "size": 14682,
      "type": "notebook",
      "writable": true
    },
    {
      "content": null,
      "created": "2026-06-28T23:09:01.059727Z",
      "format": null,
      "hash": null,
      "hash_algorithm": null,
      "last_modified": "2026-06-28T23:08:30.427697Z",
      "mimetype": null,
      "name": "session-03-a.ipynb",
      "path": "session-03-a.ipynb",
      "size": 7696,
      "type": "notebook",
      "writable": true
    }
  ],
  "created": "2026-06-28T23:09:01.059727Z",
  "format": "json",
  "hash": null,
  "hash_algorithm": null,
  "last_modified": "2026-06-28T23:09:01.059727Z",
  "mimetype": null,
  "name": "",
  "path": "",
  "size": null,
  "type": "directory",
  "writable": true
}